setup.cfg
setup.py
bin/misp_fast_lookup
misp_fast_lookup/__init__.py
misp_fast_lookup/api.py
misp_fast_lookup.egg-info/PKG-INFO
misp_fast_lookup.egg-info/SOURCES.txt
misp_fast_lookup.egg-info/dependency_links.txt
misp_fast_lookup.egg-info/requires.txt
misp_fast_lookup.egg-info/top_level.txt