Metadata-Version: 1.1
Name: misp-fast-lookup
Version: 1.0
Summary: API for MISP Redis Datastore.
Home-page: https://github.com/MISP/misp-redis-datastore
Author: Raphaël Vinot
Author-email: raphael.vinot@circl.lu
License: UNKNOWN
Platform: UNKNOWN
Classifier: License :: OSI Approved :: BSD License
Classifier: Development Status :: 5 - Production/Stable
Classifier: Environment :: Console
Classifier: Intended Audience :: Science/Research
Classifier: Intended Audience :: Telecommunications Industry
Classifier: Programming Language :: Python
Classifier: Topic :: Security
Classifier: Topic :: Internet
